ownip/Config.py
ownip/Requests.py
ownip/__init__.py
ownip/ownip.py
ownip-1.0.3.dist-info/METADATA
ownip-1.0.3.dist-info/WHEEL
ownip-1.0.3.dist-info/licenses/LICENSE
ownip-1.0.3.dist-info/RECORD
